{
  "submissionTimestamp": "2026-06-13T10:37:11.500Z",
  "runtime": "N/A",
  "memoryUsage": "N/A",
  "difficulty": "Unknown",
  "tags": [
    "Expected Complexities",
    "Company Tags",
    "Zoho",
    "Flipkart",
    "Accolite",
    "Amazon",
    "Microsoft",
    "Samsung"
  ],
  "platform": "GeeksforGeeks",
  "language": "Java (21)",
  "problemTitle": "Merge two sorted linked lists",
  "problemUrl": "https://www.geeksforgeeks.org/batch/gfg-160-problems/track/linked-list-gfg-160/problem/rotate-a-linked-list",
  "submissionId": "folbsp"
}
